oso_policy_builder/__init__.py
oso_policy_builder/actors/base.py
oso_policy_builder/actors/baseGlobal.py
oso_policy_builder/actors/builtin.py
oso_policy_builder/core/builders.py
oso_policy_builder/core/expressions.py
oso_policy_builder/core/generator.py
oso_policy_builder/core/registry.py
oso_policy_builder/resources/base.py
oso_policy_builder/utils/decorators.py
oso_policy_builder/utils/helpers.py
oso_policy_builder-0.1.0.dist-info/METADATA
oso_policy_builder-0.1.0.dist-info/WHEEL
oso_policy_builder-0.1.0.dist-info/entry_points.txt
oso_policy_builder-0.1.0.dist-info/RECORD
