Metadata-Version: 2.3
Name: oso-policy-builder
Version: 0.1.0
Summary: Pythonic builder for Oso's Polar policies
Author: Oso Security, Inc.
Requires-Python: >=3.13
Classifier: Programming Language :: Python :: 3
Classifier: Programming Language :: Python :: 3.13
